build/lib/build/lib/build/lib/build/lib/build/lib/build/lib/build/lib/build/lib/build/lib/proces/__init__.py
build/lib/build/lib/build/lib/build/lib/build/lib/build/lib/build/lib/build/lib/build/lib/proces/conf.py
build/lib/build/lib/build/lib/build/lib/build/lib/build/lib/build/lib/build/lib/build/lib/proces/masking.py
build/lib/build/lib/build/lib/build/lib/build/lib/build/lib/build/lib/build/lib/build/lib/proces/masking_test.py
build/lib/build/lib/build/lib/build/lib/build/lib/build/lib/build/lib/build/lib/build/lib/proces/preprocess.py
build/lib/build/lib/build/lib/build/lib/build/lib/build/lib/build/lib/build/lib/build/lib/proces/preprocess_test.py
build/lib/build/lib/build/lib/build/lib/build/lib/build/lib/build/lib/build/lib/build/lib/proces/util/conf.py
build/lib/build/lib/build/lib/build/lib/build/lib/build/lib/build/lib/build/lib/build/lib/proces/util/data.py
build/lib/build/lib/build/lib/build/lib/build/lib/build/lib/build/lib/build/lib/proces/__init__.py
build/lib/build/lib/build/lib/build/lib/build/lib/build/lib/build/lib/build/lib/proces/conf.py
build/lib/build/lib/build/lib/build/lib/build/lib/build/lib/build/lib/build/lib/proces/masking.py
build/lib/build/lib/build/lib/build/lib/build/lib/build/lib/build/lib/build/lib/proces/masking_test.py
build/lib/build/lib/build/lib/build/lib/build/lib/build/lib/build/lib/build/lib/proces/preprocess.py
build/lib/build/lib/build/lib/build/lib/build/lib/build/lib/build/lib/build/lib/proces/preprocess_test.py
build/lib/build/lib/build/lib/build/lib/build/lib/build/lib/build/lib/build/lib/proces/util/conf.py
build/lib/build/lib/build/lib/build/lib/build/lib/build/lib/build/lib/build/lib/proces/util/data.py
build/lib/build/lib/build/lib/build/lib/build/lib/build/lib/build/lib/proces/__init__.py
build/lib/build/lib/build/lib/build/lib/build/lib/build/lib/build/lib/proces/conf.py
build/lib/build/lib/build/lib/build/lib/build/lib/build/lib/build/lib/proces/masking.py
proces-0.1.6.dist-info/LICENSE
proces-0.1.6.dist-info/METADATA
proces-0.1.6.dist-info/WHEEL
proces-0.1.6.dist-info/top_level.txt
proces-0.1.6.dist-info/zip-safe
proces-0.1.6.dist-info/RECORD
