Metadata-Version: 2.1
Name: proces
Version: 0.1.6
Summary: text preprocess.
Home-page: https://github.com/Ailln/proces
Author: Ailln
Author-email: kinggreenhall@gmail.com
License: MIT License
Classifier: Programming Language :: Python :: 3
Classifier: Programming Language :: Python :: 3.6
Classifier: Programming Language :: Python :: 3.7
Classifier: Programming Language :: Python :: 3.8
Classifier: Programming Language :: Python :: 3.9
Classifier: License :: OSI Approved :: MIT License
Classifier: Operating System :: OS Independent
Requires-Python: >=3.6
License-File: LICENSE
Requires-Dist: ruamel.yaml (>=0.16.5)
